[
  {
    "userDiscoveryId": "212",
    "userDiscoveryUrlId": "212-georg-deutsch",
    "userName": "Georg Deutsch",
    "teachingDiscoveryId": "1638614",
    "title": "Dissertation Committee for Kayla A Steward (Ad Hoc Committee Member)",
    "status": "No longer on student's committee or student has graduated",
    "startDate": "2017-05-31T00:00:00-05:00",
    "endDate": "2020-08-15T00:00:00-05:00"
  },
  {
    "userDiscoveryId": "212",
    "userDiscoveryUrlId": "212-georg-deutsch",
    "userName": "Georg Deutsch",
    "teachingDiscoveryId": "1632831",
    "title": "Dissertation Committee for Jacquelynn D Nicosia (Ad Hoc Committee Member)",
    "status": "No longer on student's committee or student has graduated",
    "startDate": "2011-05-25T00:00:00-05:00",
    "endDate": "2012-08-06T00:00:00-05:00"
  },
  {
    "userDiscoveryId": "212",
    "userDiscoveryUrlId": "212-georg-deutsch",
    "userName": "Georg Deutsch",
    "teachingDiscoveryId": "1624976",
    "title": "Dissertation Committee for Rajiv G Menon (Ad Hoc Committee Member)",
    "status": "No longer on student's committee or student has graduated",
    "startDate": "2009-05-18T00:00:00-05:00",
    "endDate": "2010-12-15T00:00:00-06:00"
  },
  {
    "userDiscoveryId": "212",
    "userDiscoveryUrlId": "212-georg-deutsch",
    "userName": "Georg Deutsch",
    "teachingDiscoveryId": "2422302",
    "title": "Thesis Committee for Hrishikesh D Deshpande (Ad Hoc Committee Member)",
    "status": "No longer on student's committee or student has graduated",
    "startDate": "2007-12-12T00:00:00-06:00",
    "endDate": "2009-05-09T00:00:00-05:00"
  }
]