[
  {
    "userDiscoveryId": "2423",
    "userDiscoveryUrlId": "2423-christopher-waldron",
    "userName": "Christopher Waldron",
    "teachingDiscoveryId": "2979628",
    "title": "Thesis Committee for Wessam Alaa Abd-Elghany (Committee Member)",
    "status": "Current committee member",
    "startDate": "2024-01-17T00:00:00-06:00",
    "endDate": null
  },
  {
    "userDiscoveryId": "2423",
    "userDiscoveryUrlId": "2423-christopher-waldron",
    "userName": "Christopher Waldron",
    "teachingDiscoveryId": "2818122",
    "title": "Dissertation Committee for Goodnews E Amieghemen (Committee Member)",
    "status": "Current committee member",
    "startDate": "2023-08-25T00:00:00-05:00",
    "endDate": null
  },
  {
    "userDiscoveryId": "2423",
    "userDiscoveryUrlId": "2423-christopher-waldron",
    "userName": "Christopher Waldron",
    "teachingDiscoveryId": "2768863",
    "title": "Thesis Committee for Ebisidor Jeremiah Agberebi (Committee Member)",
    "status": "Current committee member",
    "startDate": "2023-04-13T00:00:00-05:00",
    "endDate": null
  },
  {
    "userDiscoveryId": "2423",
    "userDiscoveryUrlId": "2423-christopher-waldron",
    "userName": "Christopher Waldron",
    "teachingDiscoveryId": "2701449",
    "title": "Thesis Committee for Krenar Krasniqi (Committee Member)",
    "status": "Current committee member",
    "startDate": "2022-12-06T00:00:00-06:00",
    "endDate": null
  },
  {
    "userDiscoveryId": "2423",
    "userDiscoveryUrlId": "2423-christopher-waldron",
    "userName": "Christopher Waldron",
    "teachingDiscoveryId": "2532088",
    "title": "Thesis Committee for Alysia Carlisle (Committee Member)",
    "status": "Current committee member",
    "startDate": "2022-08-29T00:00:00-05:00",
    "endDate": null
  },
  {
    "userDiscoveryId": "2423",
    "userDiscoveryUrlId": "2423-christopher-waldron",
    "userName": "Christopher Waldron",
    "teachingDiscoveryId": "2429765",
    "title": "Thesis Committee for Charles Agusiobo (Committee Member)",
    "status": "No longer on student's committee or student has graduated",
    "startDate": "2021-05-11T00:00:00-05:00",
    "endDate": "2022-08-13T00:00:00-05:00"
  },
  {
    "userDiscoveryId": "2423",
    "userDiscoveryUrlId": "2423-christopher-waldron",
    "userName": "Christopher Waldron",
    "teachingDiscoveryId": "2386679",
    "title": "Thesis Committee for Nicholas Okai (Committee Member)",
    "status": "No longer on student's committee or student has graduated",
    "startDate": "2020-09-01T00:00:00-05:00",
    "endDate": "2021-08-14T00:00:00-05:00"
  },
  {
    "userDiscoveryId": "2423",
    "userDiscoveryUrlId": "2423-christopher-waldron",
    "userName": "Christopher Waldron",
    "teachingDiscoveryId": "2314578",
    "title": "Thesis Committee for Matthew L Blackstone (Committee Member)",
    "status": "No longer on student's committee or student has graduated",
    "startDate": "2020-01-24T00:00:00-06:00",
    "endDate": "2020-05-02T00:00:00-05:00"
  },
  {
    "userDiscoveryId": "2423",
    "userDiscoveryUrlId": "2423-christopher-waldron",
    "userName": "Christopher Waldron",
    "teachingDiscoveryId": "2171261",
    "title": "Thesis Committee for Md Saiful Arif Khan (Committee Member)",
    "status": "No longer on student's committee or student has graduated",
    "startDate": "2019-08-08T00:00:00-05:00",
    "endDate": "2020-08-15T00:00:00-05:00"
  },
  {
    "userDiscoveryId": "2423",
    "userDiscoveryUrlId": "2423-christopher-waldron",
    "userName": "Christopher Waldron",
    "teachingDiscoveryId": "2140140",
    "title": "Thesis Committee for Akshay Yadav (Committee Member)",
    "status": "No longer on student's committee or student has graduated",
    "startDate": "2019-02-12T00:00:00-06:00",
    "endDate": "2020-08-15T00:00:00-05:00"
  },
  {
    "userDiscoveryId": "2423",
    "userDiscoveryUrlId": "2423-christopher-waldron",
    "userName": "Christopher Waldron",
    "teachingDiscoveryId": "2123444",
    "title": "Dissertation Committee for Zhenhua Shi (Committee Member)",
    "status": "No longer on student's committee or student has graduated",
    "startDate": "2018-11-27T00:00:00-06:00",
    "endDate": "2020-12-12T00:00:00-06:00"
  },
  {
    "userDiscoveryId": "2423",
    "userDiscoveryUrlId": "2423-christopher-waldron",
    "userName": "Christopher Waldron",
    "teachingDiscoveryId": "2066662",
    "title": "Dissertation Committee for Abdelaziz I Abdellatef (Committee Member)",
    "status": "No longer on student's committee or student has graduated",
    "startDate": "2018-08-11T00:00:00-05:00",
    "endDate": "2023-04-29T00:00:00-05:00"
  },
  {
    "userDiscoveryId": "2423",
    "userDiscoveryUrlId": "2423-christopher-waldron",
    "userName": "Christopher Waldron",
    "teachingDiscoveryId": "2042955",
    "title": "Thesis Committee for Andrew J Dameron (Committee Member)",
    "status": "Current committee member",
    "startDate": "2018-06-08T00:00:00-05:00",
    "endDate": null
  },
  {
    "userDiscoveryId": "2423",
    "userDiscoveryUrlId": "2423-christopher-waldron",
    "userName": "Christopher Waldron",
    "teachingDiscoveryId": "2030428",
    "title": "Dissertation Committee for Li He (Committee Chair & Mentor)",
    "status": "No longer on student's committee or student has graduated",
    "startDate": "2018-05-04T00:00:00-05:00",
    "endDate": "2019-12-14T00:00:00-06:00"
  },
  {
    "userDiscoveryId": "2423",
    "userDiscoveryUrlId": "2423-christopher-waldron",
    "userName": "Christopher Waldron",
    "teachingDiscoveryId": "1981939",
    "title": "Thesis Committee for Qian Huang (Committee Member)",
    "status": "No longer on student's committee or student has graduated",
    "startDate": "2018-03-14T00:00:00-05:00",
    "endDate": "2018-08-11T00:00:00-05:00"
  },
  {
    "userDiscoveryId": "2423",
    "userDiscoveryUrlId": "2423-christopher-waldron",
    "userName": "Christopher Waldron",
    "teachingDiscoveryId": "1981658",
    "title": "Dissertation Committee for Furat S Salman (Committee Member)",
    "status": "No longer on student's committee or student has graduated",
    "startDate": "2018-03-12T00:00:00-05:00",
    "endDate": "2023-04-29T00:00:00-05:00"
  }
]