[
  {
    "userDiscoveryId": "3418",
    "userDiscoveryUrlId": "3418-stephen-clarkson",
    "userName": "Stephen Clarkson",
    "teachingDiscoveryId": "3206932",
    "title": "Dissertation Committee for Abu Abdullah M Hanif (Committee Member)",
    "status": "Current committee member",
    "startDate": "2025-02-11T00:00:00-06:00",
    "endDate": null
  },
  {
    "userDiscoveryId": "3418",
    "userDiscoveryUrlId": "3418-stephen-clarkson",
    "userName": "Stephen Clarkson",
    "teachingDiscoveryId": "3094426",
    "title": "Dissertation Committee for Michael J Hankes (Committee Member)",
    "status": "Current committee member",
    "startDate": "2024-08-22T00:00:00-05:00",
    "endDate": null
  }
]