[
  {
    "userDiscoveryId": "7111",
    "userDiscoveryUrlId": "7111-yvonne-edwards",
    "userName": "Yvonne Edwards",
    "teachingDiscoveryId": "3036009",
    "title": "Dissertation Committee for Hanna Sothers (Committee Member)",
    "status": "Current committee member",
    "startDate": "2024-04-22T00:00:00-05:00",
    "endDate": null
  },
  {
    "userDiscoveryId": "7111",
    "userDiscoveryUrlId": "7111-yvonne-edwards",
    "userName": "Yvonne Edwards",
    "teachingDiscoveryId": "2985436",
    "title": "Dissertation Committee for Bitota Kabishe Lukusa-Sawalena (Committee Member)",
    "status": "Current committee member",
    "startDate": "2024-02-05T00:00:00-06:00",
    "endDate": null
  },
  {
    "userDiscoveryId": "7111",
    "userDiscoveryUrlId": "7111-yvonne-edwards",
    "userName": "Yvonne Edwards",
    "teachingDiscoveryId": "2760926",
    "title": "Dissertation Committee for Sidra Amir (Committee Member)",
    "status": "Current committee member",
    "startDate": "2023-03-24T00:00:00-05:00",
    "endDate": null
  },
  {
    "userDiscoveryId": "7111",
    "userDiscoveryUrlId": "7111-yvonne-edwards",
    "userName": "Yvonne Edwards",
    "teachingDiscoveryId": "2710912",
    "title": "Thesis Committee for Nathan F Bellis (Committee Member)",
    "status": "Current committee member",
    "startDate": "2022-12-29T00:00:00-06:00",
    "endDate": null
  },
  {
    "userDiscoveryId": "7111",
    "userDiscoveryUrlId": "7111-yvonne-edwards",
    "userName": "Yvonne Edwards",
    "teachingDiscoveryId": "2472317",
    "title": "Dissertation Committee for Catarina A Mendes Felgueira (Committee Member)",
    "status": "Current committee member",
    "startDate": "2021-10-15T00:00:00-05:00",
    "endDate": null
  }
]